README.rst
setup.py
photonemitter/__init__.py
photonemitter/__main__.py
photonemitter/config.py
photonemitter/info.py
photonemitter/output.py
photonemitter/provider.py
photonemitter/test.py
photonemitter/util.py
photonemitter.egg-info/PKG-INFO
photonemitter.egg-info/SOURCES.txt
photonemitter.egg-info/dependency_links.txt
photonemitter.egg-info/entry_points.txt
photonemitter.egg-info/top_level.txt