Metadata-Version: 1.1
Name: photonemitter
Version: 0.0.1
Summary: A simple search backend system currently designed for lighthouse
Home-page: https://github.com/lf-/photonemitter
Author: lf
Author-email: p}thon@lfcode.ca
License: MIT
Keywords: lighthouse,search
Platform: UNKNOWN
Classifier: Development Status :: 3 - Alpha
Classifier: Intended Audience :: End Users/Desktop
Classifier: Programming Language :: Python :: 3 :: Only
Classifier: License :: OSI Approved :: MIT License
Classifier: Operating System :: POSIX :: Linux
Classifier: Topic :: Utilities
